LICENSE
MANIFEST.in
README.md
setup.cfg
setup.py
agape/__init__.py
agape/db/__init__.py
agape/db/fields.py
agape/db/middleware.py
agape/db/request.py
agape_db.egg-info/PKG-INFO
agape_db.egg-info/SOURCES.txt
agape_db.egg-info/dependency_links.txt
agape_db.egg-info/requires.txt
agape_db.egg-info/top_level.txt