Metadata-Version: 2.1
Name: agape-db
Version: 0.0.1
Summary: Field factories for Django models.
Home-page: https://gitlab.com/MiverikMinett/agape
Author: Maverik Minett
Author-email: maverik.minett@gmail.com
License: All rights reserved.
Platform: UNKNOWN
Classifier: Environment :: Web Environment
Classifier: Framework :: Django
Classifier: Intended Audience :: Developers
Classifier: Operating System :: OS Independent
Classifier: Programming Language :: Python
